wellapi/__init__.py
wellapi/__main__.py
wellapi/applications.py
wellapi/awsmodel.py
wellapi/convertors.py
wellapi/datastructures.py
wellapi/exception_handlers.py
wellapi/exceptions.py
wellapi/models.py
wellapi/params.py
wellapi/routing.py
wellapi/security.py
wellapi/testclient.py
wellapi/utils.py
wellapi/build/__init__.py
wellapi/build/cdk.py
wellapi/build/packager.py
wellapi/cli/__init__.py
wellapi/cli/main.py
wellapi/dependencies/__init__.py
wellapi/dependencies/models.py
wellapi/dependencies/utils.py
wellapi/local/__init__.py
wellapi/local/router.py
wellapi/local/server.py
wellapi/middleware/__init__.py
wellapi/middleware/base.py
wellapi/middleware/cors.py
wellapi/middleware/error.py
wellapi/middleware/exceptions.py
wellapi/middleware/main.py
wellapi/openapi/__init__.py
wellapi/openapi/docs.py
wellapi/openapi/models.py
wellapi/openapi/security_model.py
wellapi/openapi/utils.py
wellapi/telemetry/__init__.py
wellapi/telemetry/middleware.py
wellapi/telemetry/telemetry.py
wellapi-0.9.5.dist-info/METADATA
wellapi-0.9.5.dist-info/WHEEL
wellapi-0.9.5.dist-info/entry_points.txt
wellapi-0.9.5.dist-info/RECORD
