Metadata-Version: 2.4
Name: wellapi
Version: 0.9.5
Summary: A simple web framework for aws lambda
Author-email: romayuhym <romayuhym@gmail.com>
Requires-Python: >=3.12
Requires-Dist: email-validator>=2.3.0
Requires-Dist: pydantic==2.11.4
Requires-Dist: typing-extensions>=4.15.0
Provides-Extra: deploy
Requires-Dist: aws-cdk-lib>=2.222.0; extra == 'deploy'
Requires-Dist: constructs>=10.0.0; extra == 'deploy'
Provides-Extra: local
Requires-Dist: click>=8.3.0; extra == 'local'
Requires-Dist: httpx>=0.28.1; extra == 'local'
Requires-Dist: uvicorn==0.35.0; extra == 'local'
Provides-Extra: telemetry
Requires-Dist: opentelemetry-sdk>=1.38.0; extra == 'telemetry'
